mst/googlelib/GoogleSDK.py
mst/googlelib/__init__.py
mst/googlelib/lazy_load.py
mst/googlelib/models/__init__.py
mst/googlelib/models/group.py
mst/googlelib/models/member.py
mst/googlelib/models/user.py
mst_googlelib-2.0.3.dist-info/METADATA
mst_googlelib-2.0.3.dist-info/WHEEL
mst_googlelib-2.0.3.dist-info/top_level.txt
mst_googlelib-2.0.3.dist-info/RECORD
